bioplottemplates/__init__.py
bioplottemplates/__main__.py
bioplottemplates/cli.py
bioplottemplates/cli_labeldots.py
bioplottemplates/cli_param.py
bioplottemplates/logger.py
bioplottemplates/libs/libcli.py
bioplottemplates/libs/libio.py
bioplottemplates/libs/libmsg.py
bioplottemplates/libs/libutil.py
bioplottemplates/plots/__init__.py
bioplottemplates/plots/label_dots.py
bioplottemplates/plots/param.py
bioplottemplates-0.1.1.dist-info/AUTHORS.rst
bioplottemplates-0.1.1.dist-info/LICENSE
bioplottemplates-0.1.1.dist-info/METADATA
bioplottemplates-0.1.1.dist-info/WHEEL
bioplottemplates-0.1.1.dist-info/entry_points.txt
bioplottemplates-0.1.1.dist-info/top_level.txt
bioplottemplates-0.1.1.dist-info/RECORD
